n4e_py_adv/__init__.py
n4e_py_adv/task1_complex.py
n4e_py_adv-0.1.4.dist-info/METADATA
n4e_py_adv-0.1.4.dist-info/WHEEL
n4e_py_adv-0.1.4.dist-info/RECORD
