Metadata-Version: 2.3
Name: n4e-py-adv
Version: 0.1.4
Summary: 
Author: ilya.palkanov
Author-email: ispalkanov@rt-dc.ru
Requires-Python: >=3.11
Classifier: Programming Language :: Python :: 3
Classifier: Programming Language :: Python :: 3.11
Classifier: Programming Language :: Python :: 3.12
Classifier: Programming Language :: Python :: 3.13
Requires-Dist: pyyaml (>=6.0.2,<7.0.0)
Requires-Dist: requests (>=2.32.4,<3.0.0)
